goldy/__init__.py
goldy/_goldy.cpython-312-darwin.so
goldy/py.typed
goldy-0.1.0.dist-info/METADATA
goldy-0.1.0.dist-info/WHEEL
goldy-0.1.0.dist-info/RECORD
