Metadata-Version: 2.4
Name: goldy
Version: 0.1.0
Classifier: Development Status :: 3 - Alpha
Classifier: Intended Audience :: Developers
Classifier: License :: OSI Approved :: MIT License
Classifier: Programming Language :: Python :: 3
Classifier: Programming Language :: Python :: 3.9
Classifier: Programming Language :: Python :: 3.10
Classifier: Programming Language :: Python :: 3.11
Classifier: Programming Language :: Python :: 3.12
Classifier: Programming Language :: Rust
Classifier: Topic :: Multimedia :: Graphics
Classifier: Topic :: Scientific/Engineering :: Visualization
Requires-Dist: numpy>=1.20
Requires-Dist: pytest>=7.0 ; extra == 'dev'
Requires-Dist: pillow>=9.0 ; extra == 'dev'
Provides-Extra: dev
Summary: Python bindings for the Goldy GPU library
Keywords: gpu,graphics,vulkan,rendering,compute
Author: Mohamed Koubaa
License: MIT
Requires-Python: >=3.9
Project-URL: Documentation, https://github.com/koubaa/goldy#readme
Project-URL: Homepage, https://github.com/koubaa/goldy
Project-URL: Repository, https://github.com/koubaa/goldy
